wikiwho/__init__.py
wikiwho/io.py
wikiwho/structures.py
wikiwho/wikiwho_simple.py
wikiwho_pickle-1.1.1.dist-info/LICENSE
wikiwho_pickle-1.1.1.dist-info/METADATA
wikiwho_pickle-1.1.1.dist-info/WHEEL
wikiwho_pickle-1.1.1.dist-info/top_level.txt
wikiwho_pickle-1.1.1.dist-info/RECORD
